{
  "svo_order_rules": [
      {
          "pattern": "சிறுவர்களை அழைத்தாள் ஆசிரியர் வகுப்பில்",
          "description": "Corrects the order from Object-Verb-Subject to Subject-Object-Verb",
          "correction": "ஆசிரியர் சிறுவர்களை வகுப்பில் அழைத்தார்"
      },
      {
          "pattern": "தோழன் பார்வையை மறைத்தான் மரம் தோட்டத்தில்",
          "description": "Reorders the sentence to place the subject at the beginning for clarity",
          "correction": "தோட்டத்தில் மரம் தோழனின் பார்வையை மறைத்தது"
      },
      {
          "pattern": "மெய்மறந்தார் பயணி காட்டில் அழகை கண்டது",
          "description": "Adjusts the subject to the beginning of the sentence",
          "correction": "பயணி காட்டில் அழகை கண்டதும் மெய்மறந்தார்"
      },
      {
          "pattern": "சிறுவர்கள் பந்தை தூக்கியார் மைதானத்தில்",
          "description": "Corrects the order from Object-Verb-Subject to Subject-Object-Verb",
          "correction": "மைதானத்தில் சிறுவர்கள் பந்தை தூக்கியார்கள்"
      }
  ]
}
